Metadata-Version: 2.1
Name: selfbotdiscord
Version: 0.0.9
Summary: Discord self bot module
Home-page: UNKNOWN
Author: Emrovsky
Author-email: eemrovsky@gmail.com
License: MIT
Keywords: discord
Platform: UNKNOWN
Classifier: Development Status :: 5 - Production/Stable
Classifier: Intended Audience :: Education
Classifier: Operating System :: Microsoft :: Windows :: Windows 10
Classifier: License :: OSI Approved :: MIT License
Classifier: Programming Language :: Python :: 3
